Metadata-Version: 1.1
Name: collectd-puppet
Version: 2.0.0
Summary: Collectd Plugin to Monitor Puppet Agents
Home-page: https://github.com/cernops/collectd-puppet
Author: Steve Traylen
Author-email: steve.traylen@cern.ch
License: Apache II
Keywords: collectd puppet monitoring
Platform: UNKNOWN
Classifier: Development Status :: 4 - Beta
Classifier: Intended Audience :: System Administrators
Classifier: Operating System :: POSIX :: Linux
Classifier: Programming Language :: Python
Classifier: Topic :: System :: Monitoring
